Metadata-Version: 2.4
Name: alignparse
Version: 0.8.0
Summary: Align sequences and then parse features.
Home-page: https://github.com/jbloomlab/alignparse
Download-URL: https://github.com/jbloomlab/alignparse/tarball/0.8.0
Author: `the Bloom lab <https://jbloomlab.org/>`_
Author-email: jbloom@fredhutch.org
License: GPLv3
Platform: Linux and Mac OS X.
License-File: LICENSE.txt
Requires-Dist: biopython>=1.73
Requires-Dist: dna_features_viewer>=1.0.0
Requires-Dist: matplotlib>=3.0.0
Requires-Dist: numpy>=1.17
Requires-Dist: packaging
Requires-Dist: pandas>=0.25.1
Requires-Dist: pathos>=0.2.4
Requires-Dist: plotnine>=0.6
Requires-Dist: pysam!=0.22.1
Requires-Dist: regex>=2.5.33
Requires-Dist: scipy>=1.2
Requires-Dist: pyyaml>=5.1.1
Dynamic: author
Dynamic: author-email
Dynamic: description
Dynamic: download-url
Dynamic: home-page
Dynamic: license
Dynamic: license-file
Dynamic: platform
Dynamic: requires-dist
Dynamic: summary
